encryptoenv/CLI.py
encryptoenv/EnvFile.py
encryptoenv/__init__.py
encryptoenv/__main__.py
encryptoenv-0.0.2.dist-info/LICENSE
encryptoenv-0.0.2.dist-info/METADATA
encryptoenv-0.0.2.dist-info/WHEEL
encryptoenv-0.0.2.dist-info/entry_points.txt
encryptoenv-0.0.2.dist-info/top_level.txt
encryptoenv-0.0.2.dist-info/RECORD
