Metadata-Version: 2.1
Name: encryptoenv
Version: 0.0.2
Summary: With one command, you can setup and encrypt your environment variables.
Home-page: https://github.com/jgrugru/encrypto-env
Author: Jeff Gruenbaum
Author-email: jeff.gruenbaum@gmail.com
License: MIT
Keywords: encryption,environment_variables,env,dotenv,python,environment
Platform: UNKNOWN
Classifier: License :: OSI Approved :: MIT License
Classifier: Programming Language :: Python :: 3
Classifier: Programming Language :: Python :: 3.7
Requires-Dist: fileflamingo (==0.0.6)
